LICENSE
MANIFEST.in
README.rst
setup.cfg
setup.py
etitle/LICENSE
etitle/README.md
etitle/__init__.py
etitle/etitle.py
etitle/test_parse.py
etitle/test_parts.py
etitle.egg-info/PKG-INFO
etitle.egg-info/SOURCES.txt
etitle.egg-info/dependency_links.txt
etitle.egg-info/top_level.txt
etitle/sample/billy {_of=chicago}/Section 5{%colon%}10{%colon% Behavior for }Introspection.txt
etitle/sample/billy {_of=chicago}/{%quotes%}inner{%quotes% and %quotes%}outer{%quotes% of }Psychological Analysis.txt
etitle/sample/billy {_of=chicago}/{The Importance of} Continual Regression Analysis;mathematics.txt
etitle/sample/james==king/Topological Analysis;mathematics.txt
etitle/sample/s{cott }james/$ - cv.txt
etitle/sample/s{cott }james/$ - resume.txt
etitle/sample/s{cott }james/fundamental-process-of-behavior.txt
etitle/sample/s{cott }james/{What is }Illustrative { and Analytic Economics%questionmark%}.txt
etitle/sample/{=s.=b. }smith/lectures/{On the }2nd Person;2nd=person;mathematics;psychology.txt