Metadata-Version: 1.1
Name: etitle
Version: 1.0.2
Summary: Enables storage and retrieval of extended metadata using filename.
Home-page: https://github.com/davidbetz/pyetitle
Author: David Betz
Author-email: dfb@davidbetz.net
License: UNKNOWN
Keywords: metadata,filename
Platform: UNKNOWN
Classifier: Intended Audience :: Developers
Classifier: Topic :: Software Development :: Build Tools
Classifier: License :: OSI Approved :: MIT License
Classifier: Programming Language :: Python :: 2.7
Classifier: Programming Language :: Python :: 3.6
